{
  "id": "modelix",
  "realm": "modelix",
  "displayNameHtml": "<img src=\"../../../../public/logo-with-small-text-dark.svg\" style=\"max-width:300px\" />",
  "notBefore": 0,
  "defaultSignatureAlgorithm": "RS256",
  "revokeRefreshToken": false,
  "refreshTokenMaxReuse": 0,
  "accessTokenLifespan": 36000,
  "accessTokenLifespanForImplicitFlow": 36000,
  "ssoSessionIdleTimeout": 86400,
  "ssoSessionMaxLifespan": 604800,
  "ssoSessionIdleTimeoutRememberMe": 0,
  "ssoSessionMaxLifespanRememberMe": 0,
  "offlineSessionIdleTimeout": 2592000,
  "offlineSessionMaxLifespanEnabled": false,
  "offlineSessionMaxLifespan": 5184000,
  "clientSessionIdleTimeout": 0,
  "clientSessionMaxLifespan": 0,
  "clientOfflineSessionIdleTimeout": 0,
  "clientOfflineSessionMaxLifespan": 0,
  "accessCodeLifespan": 60,
  "accessCodeLifespanUserAction": 300,
  "accessCodeLifespanLogin": 1800,
  "actionTokenGeneratedByAdminLifespan": 43200,
  "actionTokenGeneratedByUserLifespan": 300,
  "oauth2DeviceCodeLifespan": 600,
  "oauth2DevicePollingInterval": 5,
  "enabled": true,
  "sslRequired": "none",
  "registrationAllowed": true,
  "registrationEmailAsUsername": true,
  "rememberMe": false,
  "verifyEmail": false,
  "loginWithEmailAllowed": true,
  "duplicateEmailsAllowed": false,
  "resetPasswordAllowed": false,
  "editUsernameAllowed": false,
  "bruteForceProtected": false,
  "permanentLockout": false,
  "maxFailureWaitSeconds": 900,
  "minimumQuickLoginWaitSeconds": 60,
  "waitIncrementSeconds": 60,
  "quickLoginCheckMilliSeconds": 1000,
  "maxDeltaTimeSeconds": 43200,
  "failureFactor": 30,
  "roles": {
    "realm": [
      {
        "name": "modelix-admin",
        "description": "",
        "composite": false,
        "clientRole": false,
        "containerId": "modelix",
        "attributes": {}
      },
      {
        "name": "modelix-user",
        "description": "",
        "composite": false,
        "clientRole": false,
        "containerId": "modelix",
        "attributes": {}
      },
      {
        "id": "035b6ab5-0db1-4918-bdaa-cf214f92d7d1",
        "name": "default-roles-modelix",
        "description": "${role_default-roles}",
        "composite": true,
        "composites": {
          "realm": [
            "modelix-user",
            "offline_access",
            "uma_authorization"
          ],
          "client": {
            "modelix": [
              "uma_protection"
            ],
            "account": [
              "view-profile",
              "manage-account"
            ]
          }
        },
        "clientRole": false,
        "containerId": "modelix",
        "attributes": {}
      },
      {
        "id": "1911aabc-c381-4cb2-9856-536944529558",
        "name": "uma_authorization",
        "description": "${role_uma_authorization}",
        "composite": false,
        "clientRole": false,
        "containerId": "modelix",
        "attributes": {}
      },
      {
        "id": "fe11d9c6-05b6-4603-b8f3-ff560f6a0cb0",
        "name": "offline_access",
        "description": "${role_offline-access}",
        "composite": false,
        "clientRole": false,
        "containerId": "modelix",
        "attributes": {}
      }
    ],
    "client": {
      "realm-management": [
        {
          "id": "637ffaab-ca77-4dec-917a-d2ab707ab0cf",
          "name": "realm-admin",
          "description": "${role_realm-admin}",
          "composite": true,
          "composites": {
            "client": {
              "realm-management": [
                "query-clients",
                "manage-authorization",
                "manage-events",
                "query-users",
                "view-users",
                "view-realm",
                "create-client",
                "view-events",
                "manage-identity-providers",
                "query-realms",
                "view-identity-providers",
                "manage-users",
                "impersonation",
                "view-authorization",
                "view-clients",
                "manage-clients",
                "manage-realm",
                "query-groups"
              ]
            }
          },
          "clientRole": true,
          "containerId": "404c5169-37eb-4305-a7a2-274d91091f72",
          "attributes": {}
        },
        {
          "id": "7d26d75a-aaba-47bb-952f-71a06346f0d8",
          "name": "query-clients",
          "description": "${role_query-clients}",
          "composite": false,
          "clientRole": true,
          "containerId": "404c5169-37eb-4305-a7a2-274d91091f72",
          "attributes": {}
        },
        {
          "id": "3635af75-6fcf-4af8-95cc-4e0a514d6104",
          "name": "manage-authorization",
          "description": "${role_manage-authorization}",
          "composite": false,
          "clientRole": true,
          "containerId": "404c5169-37eb-4305-a7a2-274d91091f72",
          "attributes": {}
        },
        {
          "id": "68d8cdf5-ad03-454c-beff-20f97bdb5a69",
          "name": "manage-events",
          "description": "${role_manage-events}",
          "composite": false,
          "clientRole": true,
          "containerId": "404c5169-37eb-4305-a7a2-274d91091f72",
          "attributes": {}
        },
        {
          "id": "36ef982e-0f60-4d38-92f1-cc39377de681",
          "name": "query-users",
          "description": "${role_query-users}",
          "composite": false,
          "clientRole": true,
          "containerId": "404c5169-37eb-4305-a7a2-274d91091f72",
          "attributes": {}
        },
        {
          "id": "51d210dc-0a50-46e1-9c49-f695a3d3ec72",
          "name": "view-users",
          "description": "${role_view-users}",
          "composite": true,
          "composites": {
            "client": {
              "realm-management": [
                "query-users",
                "query-groups"
              ]
            }
          },
          "clientRole": true,
          "containerId": "404c5169-37eb-4305-a7a2-274d91091f72",
          "attributes": {}
        },
        {
          "id": "837efe8a-9ff9-48b8-bc3f-63cd1af80a60",
          "name": "view-realm",
          "description": "${role_view-realm}",
          "composite": false,
          "clientRole": true,
          "containerId": "404c5169-37eb-4305-a7a2-274d91091f72",
          "attributes": {}
        },
        {
          "id": "ef72f2b4-59b8-4dd4-a9ae-8b09ab959f36",
          "name": "create-client",
          "description": "${role_create-client}",
          "composite": false,
          "clientRole": true,
          "containerId": "404c5169-37eb-4305-a7a2-274d91091f72",
          "attributes": {}
        },
        {
          "id": "e814c616-984c-4b16-aab5-cbbadc950927",
          "name": "view-events",
          "description": "${role_view-events}",
          "composite": false,
          "clientRole": true,
          "containerId": "404c5169-37eb-4305-a7a2-274d91091f72",
          "attributes": {}
        },
        {
          "id": "f75c9373-505e-48c1-891d-f4ac1f9dce64",
          "name": "manage-identity-providers",
          "description": "${role_manage-identity-providers}",
          "composite": false,
          "clientRole": true,
          "containerId": "404c5169-37eb-4305-a7a2-274d91091f72",
          "attributes": {}
        },
        {
          "id": "b5fd00de-3780-4828-a752-48412e597572",
          "name": "query-realms",
          "description": "${role_query-realms}",
          "composite": false,
          "clientRole": true,
          "containerId": "404c5169-37eb-4305-a7a2-274d91091f72",
          "attributes": {}
        },
        {
          "id": "ad5842cf-4206-47f5-acb3-d0d2c2c58f53",
          "name": "view-identity-providers",
          "description": "${role_view-identity-providers}",
          "composite": false,
          "clientRole": true,
          "containerId": "404c5169-37eb-4305-a7a2-274d91091f72",
          "attributes": {}
        },
        {
          "id": "3c3f8c84-aa31-4100-b5fc-dc9daee703db",
          "name": "manage-users",
          "description": "${role_manage-users}",
          "composite": false,
          "clientRole": true,
          "containerId": "404c5169-37eb-4305-a7a2-274d91091f72",
          "attributes": {}
        },
        {
          "id": "229ca76c-08fd-40c9-ae2a-cf9e1a7ba88b",
          "name": "impersonation",
          "description": "${role_impersonation}",
          "composite": false,
          "clientRole": true,
          "containerId": "404c5169-37eb-4305-a7a2-274d91091f72",
          "attributes": {}
        },
        {
          "id": "699d0961-01e0-465a-be2a-e1c1b425cabc",
          "name": "view-authorization",
          "description": "${role_view-authorization}",
          "composite": false,
          "clientRole": true,
          "containerId": "404c5169-37eb-4305-a7a2-274d91091f72",
          "attributes": {}
        },
        {
          "id": "37460ff0-e70a-4f3c-bcfc-d97944cf66c8",
          "name": "view-clients",
          "description": "${role_view-clients}",
          "composite": true,
          "composites": {
            "client": {
              "realm-management": [
                "query-clients"
              ]
            }
          },
          "clientRole": true,
          "containerId": "404c5169-37eb-4305-a7a2-274d91091f72",
          "attributes": {}
        },
        {
          "id": "6d399a44-b8f8-4b67-8bea-61041a2714ea",
          "name": "manage-clients",
          "description": "${role_manage-clients}",
          "composite": false,
          "clientRole": true,
          "containerId": "404c5169-37eb-4305-a7a2-274d91091f72",
          "attributes": {}
        },
        {
          "id": "6fe9dc4a-6d5b-4f34-aeab-a2f434572536",
          "name": "manage-realm",
          "description": "${role_manage-realm}",
          "composite": false,
          "clientRole": true,
          "containerId": "404c5169-37eb-4305-a7a2-274d91091f72",
          "attributes": {}
        },
        {
          "id": "d4b81d86-5f69-4014-8be0-4830456bfa80",
          "name": "query-groups",
          "description": "${role_query-groups}",
          "composite": false,
          "clientRole": true,
          "containerId": "404c5169-37eb-4305-a7a2-274d91091f72",
          "attributes": {}
        }
      ],
      "security-admin-console": [],
      "admin-cli": [],
      "modelix": [
        {
          "id": "ab3524db-4db2-4ec2-bcf8-891e1256b19d",
          "name": "uma_protection",
          "composite": false,
          "clientRole": true,
          "containerId": "42312d86-3a77-42b7-8b99-ebd072931c71",
          "attributes": {}
        }
      ],
      "account-console": [],
      "broker": [
        {
          "id": "cc5a71c9-4314-4110-964e-171284f52018",
          "name": "read-token",
          "description": "${role_read-token}",
          "composite": false,
          "clientRole": true,
          "containerId": "477cd726-e1f5-4a6c-bf93-a0f0f423f454",
          "attributes": {}
        }
      ],
      "external-mps": [],
      "account": [
        {
          "id": "d14e9f1f-62b0-4996-9507-6c40f33d90a8",
          "name": "delete-account",
          "description": "${role_delete-account}",
          "composite": false,
          "clientRole": true,
          "containerId": "fa94ba3f-344a-46fa-8fe0-571155cc68d8",
          "attributes": {}
        },
        {
          "id": "ec3c8727-572f-4188-b04d-69775e3f0555",
          "name": "view-profile",
          "description": "${role_view-profile}",
          "composite": false,
          "clientRole": true,
          "containerId": "fa94ba3f-344a-46fa-8fe0-571155cc68d8",
          "attributes": {}
        },
        {
          "id": "e2fb082f-0af8-49fa-8983-3245c3c93290",
          "name": "manage-account-links",
          "description": "${role_manage-account-links}",
          "composite": false,
          "clientRole": true,
          "containerId": "fa94ba3f-344a-46fa-8fe0-571155cc68d8",
          "attributes": {}
        },
        {
          "id": "fceea979-a84b-467c-8f5b-ae9ffb1448a3",
          "name": "manage-consent",
          "description": "${role_manage-consent}",
          "composite": true,
          "composites": {
            "client": {
              "account": [
                "view-consent"
              ]
            }
          },
          "clientRole": true,
          "containerId": "fa94ba3f-344a-46fa-8fe0-571155cc68d8",
          "attributes": {}
        },
        {
          "id": "c138d625-df3c-4770-9b9e-3fabd2c36113",
          "name": "view-consent",
          "description": "${role_view-consent}",
          "composite": false,
          "clientRole": true,
          "containerId": "fa94ba3f-344a-46fa-8fe0-571155cc68d8",
          "attributes": {}
        },
        {
          "id": "a7e7427c-aa5e-4a73-a702-60a82c1414e7",
          "name": "view-applications",
          "description": "${role_view-applications}",
          "composite": false,
          "clientRole": true,
          "containerId": "fa94ba3f-344a-46fa-8fe0-571155cc68d8",
          "attributes": {}
        },
        {
          "id": "e1452c44-5d7b-41eb-91c5-262beb384ddb",
          "name": "manage-account",
          "description": "${role_manage-account}",
          "composite": true,
          "composites": {
            "client": {
              "account": [
                "manage-account-links"
              ]
            }
          },
          "clientRole": true,
          "containerId": "fa94ba3f-344a-46fa-8fe0-571155cc68d8",
          "attributes": {}
        }
      ]
    }
  },
  "groups": [],
  "defaultRole": {
    "id": "035b6ab5-0db1-4918-bdaa-cf214f92d7d1",
    "name": "default-roles-modelix",
    "description": "${role_default-roles}",
    "composite": true,
    "clientRole": false,
    "containerId": "modelix"
  },
  "requiredCredentials": [
    "password"
  ],
  "otpPolicyType": "totp",
  "otpPolicyAlgorithm": "HmacSHA1",
  "otpPolicyInitialCounter": 0,
  "otpPolicyDigits": 6,
  "otpPolicyLookAheadWindow": 1,
  "otpPolicyPeriod": 30,
  "otpSupportedApplications": [
    "FreeOTP",
    "Google Authenticator"
  ],
  "webAuthnPolicyRpEntityName": "keycloak",
  "webAuthnPolicySignatureAlgorithms": [
    "ES256"
  ],
  "webAuthnPolicyRpId": "",
  "webAuthnPolicyAttestationConveyancePreference": "not specified",
  "webAuthnPolicyAuthenticatorAttachment": "not specified",
  "webAuthnPolicyRequireResidentKey": "not specified",
  "webAuthnPolicyUserVerificationRequirement": "not specified",
  "webAuthnPolicyCreateTimeout": 0,
  "webAuthnPolicyAvoidSameAuthenticatorRegister": false,
  "webAuthnPolicyAcceptableAaguids": [],
  "webAuthnPolicyPasswordlessRpEntityName": "keycloak",
  "webAuthnPolicyPasswordlessSignatureAlgorithms": [
    "ES256"
  ],
  "webAuthnPolicyPasswordlessRpId": "",
  "webAuthnPolicyPasswordlessAttestationConveyancePreference": "not specified",
  "webAuthnPolicyPasswordlessAuthenticatorAttachment": "not specified",
  "webAuthnPolicyPasswordlessRequireResidentKey": "not specified",
  "webAuthnPolicyPasswordlessUserVerificationRequirement": "not specified",
  "webAuthnPolicyPasswordlessCreateTimeout": 0,
  "webAuthnPolicyPasswordlessAvoidSameAuthenticatorRegister": false,
  "webAuthnPolicyPasswordlessAcceptableAaguids": [],
  "users": [
    {
      "id": "b32483e8-087a-41ba-9aef-9426b7d826a1",
      "createdTimestamp": 1656697803950,
      "username": "service-account-modelix",
      "enabled": true,
      "totp": false,
      "emailVerified": false,
      "serviceAccountClientId": "modelix",
      "disableableCredentialTypes": [],
      "requiredActions": [],
      "realmRoles": [
        "default-roles-modelix",
        "modelix-admin"
      ],
      "clientRoles": {
        "modelix": [
          "uma_protection"
        ]
      },
      "notBefore": 0,
      "groups": []
    }
  ],
  "scopeMappings": [
    {
      "clientScope": "offline_access",
      "roles": [
        "offline_access"
      ]
    }
  ],
  "clientScopeMappings": {
    "account": [
      {
        "client": "account-console",
        "roles": [
          "manage-account"
        ]
      }
    ]
  },
  "clients": [
    {
      "id": "fa94ba3f-344a-46fa-8fe0-571155cc68d8",
      "clientId": "account",
      "name": "${client_account}",
      "rootUrl": "${authBaseUrl}",
      "baseUrl": "/realms/modelix/account/",
      "surrogateAuthRequired": false,
      "enabled": true,
      "alwaysDisplayInConsole": false,
      "clientAuthenticatorType": "client-secret",
      "redirectUris": [
        "/realms/modelix/account/*"
      ],
      "webOrigins": [],
      "notBefore": 0,
      "bearerOnly": false,
      "consentRequired": false,
      "standardFlowEnabled": true,
      "implicitFlowEnabled": false,
      "directAccessGrantsEnabled": false,
      "serviceAccountsEnabled": false,
      "publicClient": true,
      "frontchannelLogout": false,
      "protocol": "openid-connect",
      "attributes": {},
      "authenticationFlowBindingOverrides": {},
      "fullScopeAllowed": false,
      "nodeReRegistrationTimeout": 0,
      "defaultClientScopes": [
        "web-origins",
        "acr",
        "profile",
        "roles",
        "email"
      ],
      "optionalClientScopes": [
        "address",
        "phone",
        "offline_access",
        "microprofile-jwt"
      ]
    },
    {
      "id": "3c31077c-7fa2-43eb-9505-49d78f8204ba",
      "clientId": "account-console",
      "name": "${client_account-console}",
      "rootUrl": "${authBaseUrl}",
      "baseUrl": "/realms/modelix/account/",
      "surrogateAuthRequired": false,
      "enabled": true,
      "alwaysDisplayInConsole": false,
      "clientAuthenticatorType": "client-secret",
      "redirectUris": [
        "/realms/modelix/account/*"
      ],
      "webOrigins": [],
      "notBefore": 0,
      "bearerOnly": false,
      "consentRequired": false,
      "standardFlowEnabled": true,
      "implicitFlowEnabled": false,
      "directAccessGrantsEnabled": false,
      "serviceAccountsEnabled": false,
      "publicClient": true,
      "frontchannelLogout": false,
      "protocol": "openid-connect",
      "attributes": {
        "pkce.code.challenge.method": "S256"
      },
      "authenticationFlowBindingOverrides": {},
      "fullScopeAllowed": false,
      "nodeReRegistrationTimeout": 0,
      "protocolMappers": [
        {
          "id": "3fc325dc-16da-4983-8028-d92f35fb7112",
          "name": "audience resolve",
          "protocol": "openid-connect",
          "protocolMapper": "oidc-audience-resolve-mapper",
          "consentRequired": false,
          "config": {}
        }
      ],
      "defaultClientScopes": [
        "web-origins",
        "acr",
        "profile",
        "roles",
        "email"
      ],
      "optionalClientScopes": [
        "address",
        "phone",
        "offline_access",
        "microprofile-jwt"
      ]
    },
    {
      "id": "7296e18b-e888-498f-82cc-6c91b927c48e",
      "clientId": "admin-cli",
      "name": "${client_admin-cli}",
      "surrogateAuthRequired": false,
      "enabled": true,
      "alwaysDisplayInConsole": false,
      "clientAuthenticatorType": "client-secret",
      "redirectUris": [],
      "webOrigins": [],
      "notBefore": 0,
      "bearerOnly": false,
      "consentRequired": false,
      "standardFlowEnabled": false,
      "implicitFlowEnabled": false,
      "directAccessGrantsEnabled": true,
      "serviceAccountsEnabled": false,
      "publicClient": true,
      "frontchannelLogout": false,
      "protocol": "openid-connect",
      "attributes": {},
      "authenticationFlowBindingOverrides": {},
      "fullScopeAllowed": false,
      "nodeReRegistrationTimeout": 0,
      "defaultClientScopes": [
        "web-origins",
        "acr",
        "profile",
        "roles",
        "email"
      ],
      "optionalClientScopes": [
        "address",
        "phone",
        "offline_access",
        "microprofile-jwt"
      ]
    },
    {
      "id": "477cd726-e1f5-4a6c-bf93-a0f0f423f454",
      "clientId": "broker",
      "name": "${client_broker}",
      "surrogateAuthRequired": false,
      "enabled": true,
      "alwaysDisplayInConsole": false,
      "clientAuthenticatorType": "client-secret",
      "redirectUris": [],
      "webOrigins": [],
      "notBefore": 0,
      "bearerOnly": true,
      "consentRequired": false,
      "standardFlowEnabled": true,
      "implicitFlowEnabled": false,
      "directAccessGrantsEnabled": false,
      "serviceAccountsEnabled": false,
      "publicClient": false,
      "frontchannelLogout": false,
      "protocol": "openid-connect",
      "attributes": {},
      "authenticationFlowBindingOverrides": {},
      "fullScopeAllowed": false,
      "nodeReRegistrationTimeout": 0,
      "defaultClientScopes": [
        "web-origins",
        "acr",
        "profile",
        "roles",
        "email"
      ],
      "optionalClientScopes": [
        "address",
        "phone",
        "offline_access",
        "microprofile-jwt"
      ]
    },
    {
      "id": "78155bc7-23db-48f3-a3c1-226c40e2fd8a",
      "clientId": "external-mps",
      "surrogateAuthRequired": false,
      "enabled": true,
      "alwaysDisplayInConsole": false,
      "clientAuthenticatorType": "client-secret",
      "redirectUris": [
        "*"
      ],
      "webOrigins": [],
      "notBefore": 0,
      "bearerOnly": false,
      "consentRequired": true,
      "standardFlowEnabled": true,
      "implicitFlowEnabled": false,
      "directAccessGrantsEnabled": true,
      "serviceAccountsEnabled": false,
      "publicClient": true,
      "frontchannelLogout": false,
      "protocol": "openid-connect",
      "attributes": {
        "saml.multivalued.roles": "false",
        "saml.force.post.binding": "false",
        "frontchannel.logout.session.required": "false",
        "oauth2.device.authorization.grant.enabled": "false",
        "backchannel.logout.revoke.offline.tokens": "false",
        "saml.server.signature.keyinfo.ext": "false",
        "use.refresh.tokens": "true",
        "oidc.ciba.grant.enabled": "false",
        "backchannel.logout.session.required": "true",
        "client_credentials.use_refresh_token": "false",
        "saml.client.signature": "false",
        "require.pushed.authorization.requests": "false",
        "saml.allow.ecp.flow": "false",
        "saml.assertion.signature": "false",
        "id.token.as.detached.signature": "false",
        "saml.encrypt": "false",
        "saml.server.signature": "false",
        "exclude.session.state.from.auth.response": "false",
        "saml.artifact.binding": "false",
        "saml_force_name_id_format": "false",
        "tls.client.certificate.bound.access.tokens": "false",
        "acr.loa.map": "{}",
        "saml.authnstatement": "false",
        "request.uris": "*",
        "display.on.consent.screen": "true",
        "token.response.type.bearer.lower-case": "false",
        "saml.onetimeuse.condition": "false"
      },
      "authenticationFlowBindingOverrides": {},
      "fullScopeAllowed": true,
      "nodeReRegistrationTimeout": -1,
      "defaultClientScopes": [
        "web-origins",
        "acr",
        "profile",
        "roles",
        "email"
      ],
      "optionalClientScopes": [
        "address",
        "phone",
        "offline_access",
        "microprofile-jwt"
      ]
    },
    {
      "id": "42312d86-3a77-42b7-8b99-ebd072931c71",
      "clientId": "modelix",
      "rootUrl": "",
      "baseUrl": "",
      "surrogateAuthRequired": false,
      "enabled": true,
      "alwaysDisplayInConsole": false,
      "clientAuthenticatorType": "client-secret",
      "secret": "${REALM_CLIENT_SECRET}",
      "redirectUris": [
        "*"
      ],
      "webOrigins": [
        "*"
      ],
      "notBefore": 0,
      "bearerOnly": false,
      "consentRequired": false,
      "standardFlowEnabled": true,
      "implicitFlowEnabled": false,
      "directAccessGrantsEnabled": true,
      "serviceAccountsEnabled": true,
      "authorizationServicesEnabled": true,
      "publicClient": false,
      "frontchannelLogout": false,
      "protocol": "openid-connect",
      "attributes": {
        "saml.force.post.binding": "false",
        "saml.multivalued.roles": "false",
        "frontchannel.logout.session.required": "false",
        "oauth2.device.authorization.grant.enabled": "true",
        "backchannel.logout.revoke.offline.tokens": "false",
        "saml.server.signature.keyinfo.ext": "false",
        "use.refresh.tokens": "true",
        "oidc.ciba.grant.enabled": "false",
        "backchannel.logout.session.required": "true",
        "client_credentials.use_refresh_token": "false",
        "require.pushed.authorization.requests": "false",
        "saml.client.signature": "false",
        "saml.allow.ecp.flow": "false",
        "id.token.as.detached.signature": "false",
        "saml.assertion.signature": "false",
        "client.secret.creation.time": "1656697803",
        "saml.encrypt": "false",
        "saml.server.signature": "false",
        "exclude.session.state.from.auth.response": "false",
        "saml.artifact.binding": "false",
        "saml_force_name_id_format": "false",
        "acr.loa.map": "{}",
        "tls.client.certificate.bound.access.tokens": "false",
        "saml.authnstatement": "false",
        "display.on.consent.screen": "false",
        "request.uris": "*",
        "token.response.type.bearer.lower-case": "false",
        "saml.onetimeuse.condition": "false"
      },
      "authenticationFlowBindingOverrides": {},
      "fullScopeAllowed": true,
      "nodeReRegistrationTimeout": -1,
      "protocolMappers": [
        {
          "id": "db9f56aa-cf90-4a17-93b6-d047b768698e",
          "name": "Client Host",
          "protocol": "openid-connect",
          "protocolMapper": "oidc-usersessionmodel-note-mapper",
          "consentRequired": false,
          "config": {
            "user.session.note": "clientHost",
            "userinfo.token.claim": "true",
            "id.token.claim": "true",
            "access.token.claim": "true",
            "claim.name": "clientHost",
            "jsonType.label": "String"
          }
        },
        {
          "id": "57adb255-e144-4899-a5d9-3d2ac9ec19c2",
          "name": "Client ID",
          "protocol": "openid-connect",
          "protocolMapper": "oidc-usersessionmodel-note-mapper",
          "consentRequired": false,
          "config": {
            "user.session.note": "clientId",
            "userinfo.token.claim": "true",
            "id.token.claim": "true",
            "access.token.claim": "true",
            "claim.name": "clientId",
            "jsonType.label": "String"
          }
        },
        {
          "id": "1dac24c5-a925-42da-9d52-bd8b735bc741",
          "name": "Client IP Address",
          "protocol": "openid-connect",
          "protocolMapper": "oidc-usersessionmodel-note-mapper",
          "consentRequired": false,
          "config": {
            "user.session.note": "clientAddress",
            "userinfo.token.claim": "true",
            "id.token.claim": "true",
            "access.token.claim": "true",
            "claim.name": "clientAddress",
            "jsonType.label": "String"
          }
        }
      ],
      "defaultClientScopes": [
        "web-origins",
        "acr",
        "profile",
        "roles",
        "email"
      ],
      "optionalClientScopes": [
        "address",
        "phone",
        "offline_access",
        "microprofile-jwt"
      ],
      "authorizationSettings": {
        "allowRemoteResourceManagement": true,
        "policyEnforcementMode": "ENFORCING",
        "resources": [
          {
            "name": "list/workspace-list",
            "type": "list",
            "ownerManagedAccess": false,
            "attributes": {},
            "uris": [],
            "scopes": [
              {"name": "add"},
              {"name": "list"},
              {"name": "read"},
              {"name": "delete"},
              {"name": "write"}
            ]
          }
        ],
        "policies": [
          {
            "name": "grant modelix-user",
            "type": "role",
            "logic": "POSITIVE",
            "decisionStrategy": "UNANIMOUS",
            "config": {
              "roles": "[{\"id\":\"modelix-user\",\"required\":false}]"
            }
          },
          {
            "name": "grant owner",
            "type": "grant-owner",
            "logic": "POSITIVE"
          },
          {
            "name": "grant modelix-admin",
            "type": "role",
            "logic": "POSITIVE",
            "decisionStrategy": "UNANIMOUS",
            "config": {
              "roles": "[{\"id\":\"modelix-admin\",\"required\":false}]"
            }
          },
          {
            "name": "owner can access owned workspaces",
            "type": "scope",
            "logic": "POSITIVE",
            "decisionStrategy": "AFFIRMATIVE",
            "config": {
              "defaultResourceType": "workspace",
              "applyPolicies": "[\"grant owner\"]",
              "scopes": "[\"write\",\"delete\",\"read\",\"list\"]"
            }
          },
          {
            "name": "modelix-user can add to workspace-list",
            "type": "scope",
            "logic": "POSITIVE",
            "decisionStrategy": "AFFIRMATIVE",
            "config": {
              "resources": "[\"list/workspace-list\"]",
              "scopes": "[\"read\", \"add\"]",
              "applyPolicies": "[\"grant modelix-user\"]"
            }
          },
          {
            "name": "modelix-user can read all workspaces",
            "type": "scope",
            "logic": "POSITIVE",
            "decisionStrategy": "AFFIRMATIVE",
            "config": {
              "defaultResourceType": "workspace",
              "scopes": "[\"read\", \"list\"]",
              "applyPolicies": "[\"grant modelix-user\"]"
            }
          },
          {
            "name": "modelix-admin can modify everything",
            "type": "scope",
            "logic": "POSITIVE",
            "decisionStrategy": "AFFIRMATIVE",
            "config": {
              "scopes": "[\"delete\",\"write\",\"read\"]",
              "applyPolicies": "[\"grant modelix-admin\"]"
            }
          }
        ],
        "scopes": [
          {
            "name": "delete"
          },
          {
            "name": "write"
          },
          {
            "name": "read"
          }
        ],
        "decisionStrategy": "AFFIRMATIVE"
      }
    },
    {
      "id": "404c5169-37eb-4305-a7a2-274d91091f72",
      "clientId": "realm-management",
      "name": "${client_realm-management}",
      "surrogateAuthRequired": false,
      "enabled": true,
      "alwaysDisplayInConsole": false,
      "clientAuthenticatorType": "client-secret",
      "redirectUris": [],
      "webOrigins": [],
      "notBefore": 0,
      "bearerOnly": true,
      "consentRequired": false,
      "standardFlowEnabled": true,
      "implicitFlowEnabled": false,
      "directAccessGrantsEnabled": false,
      "serviceAccountsEnabled": false,
      "publicClient": false,
      "frontchannelLogout": false,
      "protocol": "openid-connect",
      "attributes": {},
      "authenticationFlowBindingOverrides": {},
      "fullScopeAllowed": false,
      "nodeReRegistrationTimeout": 0,
      "defaultClientScopes": [
        "web-origins",
        "acr",
        "profile",
        "roles",
        "email"
      ],
      "optionalClientScopes": [
        "address",
        "phone",
        "offline_access",
        "microprofile-jwt"
      ]
    },
    {
      "id": "5c1b17ca-3d60-439a-875f-ee8e4f4f2846",
      "clientId": "security-admin-console",
      "name": "${client_security-admin-console}",
      "rootUrl": "${authAdminUrl}",
      "baseUrl": "/admin/modelix/console/",
      "surrogateAuthRequired": false,
      "enabled": true,
      "alwaysDisplayInConsole": false,
      "clientAuthenticatorType": "client-secret",
      "redirectUris": [
        "/admin/modelix/console/*"
      ],
      "webOrigins": [
        "+"
      ],
      "notBefore": 0,
      "bearerOnly": false,
      "consentRequired": false,
      "standardFlowEnabled": true,
      "implicitFlowEnabled": false,
      "directAccessGrantsEnabled": false,
      "serviceAccountsEnabled": false,
      "publicClient": true,
      "frontchannelLogout": false,
      "protocol": "openid-connect",
      "attributes": {
        "pkce.code.challenge.method": "S256"
      },
      "authenticationFlowBindingOverrides": {},
      "fullScopeAllowed": false,
      "nodeReRegistrationTimeout": 0,
      "protocolMappers": [
        {
          "id": "9c2612e7-8ca1-47b2-9a04-15044a005b9f",
          "name": "locale",
          "protocol": "openid-connect",
          "protocolMapper": "oidc-usermodel-attribute-mapper",
          "consentRequired": false,
          "config": {
            "userinfo.token.claim": "true",
            "user.attribute": "locale",
            "id.token.claim": "true",
            "access.token.claim": "true",
            "claim.name": "locale",
            "jsonType.label": "String"
          }
        }
      ],
      "defaultClientScopes": [
        "web-origins",
        "acr",
        "profile",
        "roles",
        "email"
      ],
      "optionalClientScopes": [
        "address",
        "phone",
        "offline_access",
        "microprofile-jwt"
      ]
    }
  ],
  "clientScopes": [
    {
      "id": "ac03bfa9-d6cd-465a-9fe3-3a60854dbee4",
      "name": "profile",
      "description": "OpenID Connect built-in scope: profile",
      "protocol": "openid-connect",
      "attributes": {
        "include.in.token.scope": "true",
        "display.on.consent.screen": "true",
        "consent.screen.text": "${profileScopeConsentText}"
      },
      "protocolMappers": [
        {
          "id": "b4dca6f2-16db-4fc1-b934-eb0e755b4b58",
          "name": "locale",
          "protocol": "openid-connect",
          "protocolMapper": "oidc-usermodel-attribute-mapper",
          "consentRequired": false,
          "config": {
            "userinfo.token.claim": "true",
            "user.attribute": "locale",
            "id.token.claim": "true",
            "access.token.claim": "true",
            "claim.name": "locale",
            "jsonType.label": "String"
          }
        },
        {
          "id": "8ca83a52-89e7-4428-b321-23c9e9132f13",
          "name": "middle name",
          "protocol": "openid-connect",
          "protocolMapper": "oidc-usermodel-attribute-mapper",
          "consentRequired": false,
          "config": {
            "userinfo.token.claim": "true",
            "user.attribute": "middleName",
            "id.token.claim": "true",
            "access.token.claim": "true",
            "claim.name": "middle_name",
            "jsonType.label": "String"
          }
        },
        {
          "id": "caebb28c-5442-4cb8-b227-204f1555f05a",
          "name": "full name",
          "protocol": "openid-connect",
          "protocolMapper": "oidc-full-name-mapper",
          "consentRequired": false,
          "config": {
            "id.token.claim": "true",
            "access.token.claim": "true",
            "userinfo.token.claim": "true"
          }
        },
        {
          "id": "e153f33b-1a62-4eb1-ac06-b6b1c58262fa",
          "name": "family name",
          "protocol": "openid-connect",
          "protocolMapper": "oidc-usermodel-property-mapper",
          "consentRequired": false,
          "config": {
            "userinfo.token.claim": "true",
            "user.attribute": "lastName",
            "id.token.claim": "true",
            "access.token.claim": "true",
            "claim.name": "family_name",
            "jsonType.label": "String"
          }
        },
        {
          "id": "fa159b20-465f-49fe-bcf4-64d53c9af9a5",
          "name": "nickname",
          "protocol": "openid-connect",
          "protocolMapper": "oidc-usermodel-attribute-mapper",
          "consentRequired": false,
          "config": {
            "userinfo.token.claim": "true",
            "user.attribute": "nickname",
            "id.token.claim": "true",
            "access.token.claim": "true",
            "claim.name": "nickname",
            "jsonType.label": "String"
          }
        },
        {
          "id": "806bce50-a6fe-418a-86f2-ea974c56365c",
          "name": "username",
          "protocol": "openid-connect",
          "protocolMapper": "oidc-usermodel-property-mapper",
          "consentRequired": false,
          "config": {
            "userinfo.token.claim": "true",
            "user.attribute": "username",
            "id.token.claim": "true",
            "access.token.claim": "true",
            "claim.name": "preferred_username",
            "jsonType.label": "String"
          }
        },
        {
          "id": "e71a943e-60f1-43c7-886f-a0e9db38f07e",
          "name": "zoneinfo",
          "protocol": "openid-connect",
          "protocolMapper": "oidc-usermodel-attribute-mapper",
          "consentRequired": false,
          "config": {
            "userinfo.token.claim": "true",
            "user.attribute": "zoneinfo",
            "id.token.claim": "true",
            "access.token.claim": "true",
            "claim.name": "zoneinfo",
            "jsonType.label": "String"
          }
        },
        {
          "id": "8359f027-b9a1-449e-a549-ec0f050578dc",
          "name": "picture",
          "protocol": "openid-connect",
          "protocolMapper": "oidc-usermodel-attribute-mapper",
          "consentRequired": false,
          "config": {
            "userinfo.token.claim": "true",
            "user.attribute": "picture",
            "id.token.claim": "true",
            "access.token.claim": "true",
            "claim.name": "picture",
            "jsonType.label": "String"
          }
        },
        {
          "id": "c0ff47f2-6880-43f9-b5f0-e43dbd6c8730",
          "name": "given name",
          "protocol": "openid-connect",
          "protocolMapper": "oidc-usermodel-property-mapper",
          "consentRequired": false,
          "config": {
            "userinfo.token.claim": "true",
            "user.attribute": "firstName",
            "id.token.claim": "true",
            "access.token.claim": "true",
            "claim.name": "given_name",
            "jsonType.label": "String"
          }
        },
        {
          "id": "b43b7da9-3c9f-42a3-bf78-9cdf4bf3056a",
          "name": "website",
          "protocol": "openid-connect",
          "protocolMapper": "oidc-usermodel-attribute-mapper",
          "consentRequired": false,
          "config": {
            "userinfo.token.claim": "true",
            "user.attribute": "website",
            "id.token.claim": "true",
            "access.token.claim": "true",
            "claim.name": "website",
            "jsonType.label": "String"
          }
        },
        {
          "id": "9e126ba3-38c7-41f8-9f49-19e120009697",
          "name": "updated at",
          "protocol": "openid-connect",
          "protocolMapper": "oidc-usermodel-attribute-mapper",
          "consentRequired": false,
          "config": {
            "userinfo.token.claim": "true",
            "user.attribute": "updatedAt",
            "id.token.claim": "true",
            "access.token.claim": "true",
            "claim.name": "updated_at",
            "jsonType.label": "long"
          }
        },
        {
          "id": "d2984c41-8f25-4b02-9913-2b6ccec4e3a7",
          "name": "gender",
          "protocol": "openid-connect",
          "protocolMapper": "oidc-usermodel-attribute-mapper",
          "consentRequired": false,
          "config": {
            "userinfo.token.claim": "true",
            "user.attribute": "gender",
            "id.token.claim": "true",
            "access.token.claim": "true",
            "claim.name": "gender",
            "jsonType.label": "String"
          }
        },
        {
          "id": "e1ec370f-f615-468b-a4ea-0d76d01b8e53",
          "name": "birthdate",
          "protocol": "openid-connect",
          "protocolMapper": "oidc-usermodel-attribute-mapper",
          "consentRequired": false,
          "config": {
            "userinfo.token.claim": "true",
            "user.attribute": "birthdate",
            "id.token.claim": "true",
            "access.token.claim": "true",
            "claim.name": "birthdate",
            "jsonType.label": "String"
          }
        },
        {
          "id": "6b54ef28-3306-480e-9654-51e21af93cc3",
          "name": "profile",
          "protocol": "openid-connect",
          "protocolMapper": "oidc-usermodel-attribute-mapper",
          "consentRequired": false,
          "config": {
            "userinfo.token.claim": "true",
            "user.attribute": "profile",
            "id.token.claim": "true",
            "access.token.claim": "true",
            "claim.name": "profile",
            "jsonType.label": "String"
          }
        }
      ]
    },
    {
      "id": "265765de-0665-440b-8613-c7c1b43e11d6",
      "name": "phone",
      "description": "OpenID Connect built-in scope: phone",
      "protocol": "openid-connect",
      "attributes": {
        "include.in.token.scope": "true",
        "display.on.consent.screen": "true",
        "consent.screen.text": "${phoneScopeConsentText}"
      },
      "protocolMappers": [
        {
          "id": "779d9770-d402-4924-8cf0-c023d57b5b36",
          "name": "phone number verified",
          "protocol": "openid-connect",
          "protocolMapper": "oidc-usermodel-attribute-mapper",
          "consentRequired": false,
          "config": {
            "userinfo.token.claim": "true",
            "user.attribute": "phoneNumberVerified",
            "id.token.claim": "true",
            "access.token.claim": "true",
            "claim.name": "phone_number_verified",
            "jsonType.label": "boolean"
          }
        },
        {
          "id": "f6d1f832-0ea6-448c-a428-b7653e892e21",
          "name": "phone number",
          "protocol": "openid-connect",
          "protocolMapper": "oidc-usermodel-attribute-mapper",
          "consentRequired": false,
          "config": {
            "userinfo.token.claim": "true",
            "user.attribute": "phoneNumber",
            "id.token.claim": "true",
            "access.token.claim": "true",
            "claim.name": "phone_number",
            "jsonType.label": "String"
          }
        }
      ]
    },
    {
      "id": "0038b7c0-76b8-4044-92cf-a28271ee5697",
      "name": "offline_access",
      "description": "OpenID Connect built-in scope: offline_access",
      "protocol": "openid-connect",
      "attributes": {
        "consent.screen.text": "${offlineAccessScopeConsentText}",
        "display.on.consent.screen": "true"
      }
    },
    {
      "id": "c4fd63e6-6e02-47be-9158-bb5bee25da62",
      "name": "email",
      "description": "OpenID Connect built-in scope: email",
      "protocol": "openid-connect",
      "attributes": {
        "include.in.token.scope": "true",
        "display.on.consent.screen": "true",
        "consent.screen.text": "${emailScopeConsentText}"
      },
      "protocolMappers": [
        {
          "id": "5bd5fd3e-2f64-46d9-beb4-9df04c670fbe",
          "name": "email verified",
          "protocol": "openid-connect",
          "protocolMapper": "oidc-usermodel-property-mapper",
          "consentRequired": false,
          "config": {
            "userinfo.token.claim": "true",
            "user.attribute": "emailVerified",
            "id.token.claim": "true",
            "access.token.claim": "true",
            "claim.name": "email_verified",
            "jsonType.label": "boolean"
          }
        },
        {
          "id": "13318425-0416-4408-ac9a-6103a34df184",
          "name": "email",
          "protocol": "openid-connect",
          "protocolMapper": "oidc-usermodel-property-mapper",
          "consentRequired": false,
          "config": {
            "userinfo.token.claim": "true",
            "user.attribute": "email",
            "id.token.claim": "true",
            "access.token.claim": "true",
            "claim.name": "email",
            "jsonType.label": "String"
          }
        }
      ]
    },
    {
      "id": "1d194781-4d0d-4362-adae-45f13ec00580",
      "name": "address",
      "description": "OpenID Connect built-in scope: address",
      "protocol": "openid-connect",
      "attributes": {
        "include.in.token.scope": "true",
        "display.on.consent.screen": "true",
        "consent.screen.text": "${addressScopeConsentText}"
      },
      "protocolMappers": [
        {
          "id": "bd8dd029-82fd-4117-9520-74bc87b561a2",
          "name": "address",
          "protocol": "openid-connect",
          "protocolMapper": "oidc-address-mapper",
          "consentRequired": false,
          "config": {
            "user.attribute.formatted": "formatted",
            "user.attribute.country": "country",
            "user.attribute.postal_code": "postal_code",
            "userinfo.token.claim": "true",
            "user.attribute.street": "street",
            "id.token.claim": "true",
            "user.attribute.region": "region",
            "access.token.claim": "true",
            "user.attribute.locality": "locality"
          }
        }
      ]
    },
    {
      "id": "affa09af-11f7-4574-beb7-7eeb67f3d1b4",
      "name": "roles",
      "description": "OpenID Connect scope for add user roles to the access token",
      "protocol": "openid-connect",
      "attributes": {
        "include.in.token.scope": "false",
        "display.on.consent.screen": "true",
        "consent.screen.text": "${rolesScopeConsentText}"
      },
      "protocolMappers": [
        {
          "id": "8f17a783-690b-420f-a40c-fc39de4d3501",
          "name": "client roles",
          "protocol": "openid-connect",
          "protocolMapper": "oidc-usermodel-client-role-mapper",
          "consentRequired": false,
          "config": {
            "user.attribute": "foo",
            "access.token.claim": "true",
            "claim.name": "resource_access.${client_id}.roles",
            "jsonType.label": "String",
            "multivalued": "true"
          }
        },
        {
          "id": "19976a15-9dae-4385-a0bf-08fb137a37df",
          "name": "realm roles",
          "protocol": "openid-connect",
          "protocolMapper": "oidc-usermodel-realm-role-mapper",
          "consentRequired": false,
          "config": {
            "user.attribute": "foo",
            "access.token.claim": "true",
            "claim.name": "realm_access.roles",
            "jsonType.label": "String",
            "multivalued": "true"
          }
        },
        {
          "id": "dcd2dc42-eecf-4736-817d-55882955d405",
          "name": "audience resolve",
          "protocol": "openid-connect",
          "protocolMapper": "oidc-audience-resolve-mapper",
          "consentRequired": false,
          "config": {}
        },
        {
          "id": "4e01c67d-7815-409a-af63-ef08cf5a3046",
          "name": "modelix aud",
          "protocol": "openid-connect",
          "protocolMapper": "oidc-audience-mapper",
          "consentRequired": false,
          "config": {
            "included.client.audience": "modelix",
            "id.token.claim": "false",
            "access.token.claim": "true",
            "userinfo.token.claim": "false"
          }
        }
      ]
    },
    {
      "id": "e5157fad-e7bd-4e5f-aaf8-8003ea344481",
      "name": "acr",
      "description": "OpenID Connect scope for add acr (authentication context class reference) to the token",
      "protocol": "openid-connect",
      "attributes": {
        "include.in.token.scope": "false",
        "display.on.consent.screen": "false"
      },
      "protocolMappers": [
        {
          "id": "d3e00b7f-f63d-4b9f-8c47-83d0e9cc7dba",
          "name": "acr loa level",
          "protocol": "openid-connect",
          "protocolMapper": "oidc-acr-mapper",
          "consentRequired": false,
          "config": {
            "id.token.claim": "true",
            "userinfo.token.claim": "true",
            "access.token.claim": "true"
          }
        }
      ]
    },
    {
      "id": "91afa1b5-ada2-4f3b-8e2e-9c7fd4f2ab40",
      "name": "microprofile-jwt",
      "description": "Microprofile - JWT built-in scope",
      "protocol": "openid-connect",
      "attributes": {
        "include.in.token.scope": "true",
        "display.on.consent.screen": "false"
      },
      "protocolMappers": [
        {
          "id": "43dad195-779a-4380-ab05-b05af32fca8c",
          "name": "upn",
          "protocol": "openid-connect",
          "protocolMapper": "oidc-usermodel-property-mapper",
          "consentRequired": false,
          "config": {
            "userinfo.token.claim": "true",
            "user.attribute": "username",
            "id.token.claim": "true",
            "access.token.claim": "true",
            "claim.name": "upn",
            "jsonType.label": "String"
          }
        },
        {
          "id": "02b7d1e5-5776-4374-9add-36403d8c2ff0",
          "name": "groups",
          "protocol": "openid-connect",
          "protocolMapper": "oidc-usermodel-realm-role-mapper",
          "consentRequired": false,
          "config": {
            "multivalued": "true",
            "userinfo.token.claim": "true",
            "user.attribute": "foo",
            "id.token.claim": "true",
            "access.token.claim": "true",
            "claim.name": "groups",
            "jsonType.label": "String"
          }
        }
      ]
    },
    {
      "id": "7eca4a5a-99d0-4474-bbc7-36ded6cfd64b",
      "name": "web-origins",
      "description": "OpenID Connect scope for add allowed web origins to the access token",
      "protocol": "openid-connect",
      "attributes": {
        "include.in.token.scope": "false",
        "display.on.consent.screen": "false",
        "consent.screen.text": ""
      },
      "protocolMappers": [
        {
          "id": "62cb2ad1-1d71-49b2-8acd-a2593aab08e1",
          "name": "allowed web origins",
          "protocol": "openid-connect",
          "protocolMapper": "oidc-allowed-origins-mapper",
          "consentRequired": false,
          "config": {}
        }
      ]
    },
    {
      "id": "d4c5de3f-9b97-421d-bb36-fdaa4763fc68",
      "name": "role_list",
      "description": "SAML role list",
      "protocol": "saml",
      "attributes": {
        "consent.screen.text": "${samlRoleListScopeConsentText}",
        "display.on.consent.screen": "true"
      },
      "protocolMappers": [
        {
          "id": "7987ec74-a0c0-4da0-b065-b66ec0ce38cf",
          "name": "role list",
          "protocol": "saml",
          "protocolMapper": "saml-role-list-mapper",
          "consentRequired": false,
          "config": {
            "single": "false",
            "attribute.nameformat": "Basic",
            "attribute.name": "Role"
          }
        }
      ]
    }
  ],
  "defaultDefaultClientScopes": [
    "role_list",
    "profile",
    "email",
    "roles",
    "web-origins",
    "acr"
  ],
  "defaultOptionalClientScopes": [
    "offline_access",
    "address",
    "phone",
    "microprofile-jwt"
  ],
  "browserSecurityHeaders": {
    "contentSecurityPolicyReportOnly": "",
    "xContentTypeOptions": "nosniff",
    "xRobotsTag": "none",
    "xFrameOptions": "SAMEORIGIN",
    "contentSecurityPolicy": "frame-src 'self'; frame-ancestors 'self'; object-src 'none';",
    "xXSSProtection": "1; mode=block",
    "strictTransportSecurity": "max-age=31536000; includeSubDomains"
  },
  "smtpServer": {},
  "eventsEnabled": false,
  "eventsListeners": [
    "jboss-logging"
  ],
  "enabledEventTypes": [],
  "adminEventsEnabled": false,
  "adminEventsDetailsEnabled": false,
  "identityProviders": [],
  "identityProviderMappers": [],
  "components": {
    "org.keycloak.services.clientregistration.policy.ClientRegistrationPolicy": [
      {
        "id": "0ee1bec8-170b-442a-8d09-22f4893bdad5",
        "name": "Allowed Protocol Mapper Types",
        "providerId": "allowed-protocol-mappers",
        "subType": "authenticated",
        "subComponents": {},
        "config": {
          "allowed-protocol-mapper-types": [
            "oidc-address-mapper",
            "oidc-full-name-mapper",
            "saml-user-attribute-mapper",
            "oidc-usermodel-property-mapper",
            "saml-user-property-mapper",
            "oidc-sha256-pairwise-sub-mapper",
            "oidc-usermodel-attribute-mapper",
            "saml-role-list-mapper"
          ]
        }
      },
      {
        "id": "ec96225b-46ee-462e-aa44-4127d1992894",
        "name": "Allowed Client Scopes",
        "providerId": "allowed-client-templates",
        "subType": "anonymous",
        "subComponents": {},
        "config": {
          "allow-default-scopes": [
            "true"
          ]
        }
      },
      {
        "id": "190766b8-f5ce-4de1-8d22-a0565ad7685f",
        "name": "Max Clients Limit",
        "providerId": "max-clients",
        "subType": "anonymous",
        "subComponents": {},
        "config": {
          "max-clients": [
            "200"
          ]
        }
      },
      {
        "id": "f4170b4c-779f-4f14-946b-5a4bd9d2096f",
        "name": "Allowed Client Scopes",
        "providerId": "allowed-client-templates",
        "subType": "authenticated",
        "subComponents": {},
        "config": {
          "allow-default-scopes": [
            "true"
          ]
        }
      },
      {
        "id": "abf72162-93df-421e-a9c6-dc6962808e1e",
        "name": "Full Scope Disabled",
        "providerId": "scope",
        "subType": "anonymous",
        "subComponents": {},
        "config": {}
      },
      {
        "id": "8c17cddf-5289-41ae-8919-e5e94f660a4c",
        "name": "Allowed Protocol Mapper Types",
        "providerId": "allowed-protocol-mappers",
        "subType": "anonymous",
        "subComponents": {},
        "config": {
          "allowed-protocol-mapper-types": [
            "oidc-usermodel-property-mapper",
            "oidc-full-name-mapper",
            "oidc-usermodel-attribute-mapper",
            "oidc-address-mapper",
            "oidc-sha256-pairwise-sub-mapper",
            "saml-role-list-mapper",
            "saml-user-property-mapper",
            "saml-user-attribute-mapper"
          ]
        }
      },
      {
        "id": "974f6d4b-1152-46df-b75b-33b61fef2645",
        "name": "Trusted Hosts",
        "providerId": "trusted-hosts",
        "subType": "anonymous",
        "subComponents": {},
        "config": {
          "host-sending-registration-request-must-match": [
            "true"
          ],
          "client-uris-must-match": [
            "true"
          ]
        }
      },
      {
        "id": "a487fd10-9eec-4916-9350-0789881188ee",
        "name": "Consent Required",
        "providerId": "consent-required",
        "subType": "anonymous",
        "subComponents": {},
        "config": {}
      }
    ],
    "org.keycloak.keys.KeyProvider": [
      {
        "id": "31c94372-1e70-4b55-abfd-0dc0ed983549",
        "name": "rsa-generated",
        "providerId": "rsa-generated",
        "subComponents": {},
        "config": {
          "priority": [
            "100"
          ]
        }
      },
      {
        "id": "2a06010c-67cb-4ea1-add1-643581ec85af",
        "name": "hmac-generated",
        "providerId": "hmac-generated",
        "subComponents": {},
        "config": {
          "priority": [
            "100"
          ],
          "algorithm": [
            "HS256"
          ]
        }
      },
      {
        "id": "784296a0-08b7-4926-8802-7a0064bb715b",
        "name": "rsa-enc-generated",
        "providerId": "rsa-enc-generated",
        "subComponents": {},
        "config": {
          "priority": [
            "100"
          ],
          "algorithm": [
            "RSA-OAEP"
          ]
        }
      },
      {
        "id": "53af327f-469f-4170-9700-ef7c068f3db0",
        "name": "aes-generated",
        "providerId": "aes-generated",
        "subComponents": {},
        "config": {
          "priority": [
            "100"
          ]
        }
      }
    ]
  },
  "internationalizationEnabled": false,
  "supportedLocales": [],
  "authenticationFlows": [
    {
      "id": "3067d051-5567-4021-a4c5-b2984d4bf211",
      "alias": "Account verification options",
      "description": "Method with which to verity the existing account",
      "providerId": "basic-flow",
      "topLevel": false,
      "builtIn": true,
      "authenticationExecutions": [
        {
          "authenticator": "idp-email-verification",
          "authenticatorFlow": false,
          "requirement": "ALTERNATIVE",
          "priority": 10,
          "autheticatorFlow": false,
          "userSetupAllowed": false
        },
        {
          "authenticatorFlow": true,
          "requirement": "ALTERNATIVE",
          "priority": 20,
          "autheticatorFlow": true,
          "flowAlias": "Verify Existing Account by Re-authentication",
          "userSetupAllowed": false
        }
      ]
    },
    {
      "id": "a3870ca4-00dd-4e7c-bbc8-287f39533b94",
      "alias": "Authentication Options",
      "description": "Authentication options.",
      "providerId": "basic-flow",
      "topLevel": false,
      "builtIn": true,
      "authenticationExecutions": [
        {
          "authenticator": "basic-auth",
          "authenticatorFlow": false,
          "requirement": "REQUIRED",
          "priority": 10,
          "autheticatorFlow": false,
          "userSetupAllowed": false
        },
        {
          "authenticator": "basic-auth-otp",
          "authenticatorFlow": false,
          "requirement": "DISABLED",
          "priority": 20,
          "autheticatorFlow": false,
          "userSetupAllowed": false
        },
        {
          "authenticator": "auth-spnego",
          "authenticatorFlow": false,
          "requirement": "DISABLED",
          "priority": 30,
          "autheticatorFlow": false,
          "userSetupAllowed": false
        }
      ]
    },
    {
      "id": "aed0453f-177f-45fa-adb4-f16bea142a3a",
      "alias": "Browser - Conditional OTP",
      "description": "Flow to determine if the OTP is required for the authentication",
      "providerId": "basic-flow",
      "topLevel": false,
      "builtIn": true,
      "authenticationExecutions": [
        {
          "authenticator": "conditional-user-configured",
          "authenticatorFlow": false,
          "requirement": "REQUIRED",
          "priority": 10,
          "autheticatorFlow": false,
          "userSetupAllowed": false
        },
        {
          "authenticator": "auth-otp-form",
          "authenticatorFlow": false,
          "requirement": "REQUIRED",
          "priority": 20,
          "autheticatorFlow": false,
          "userSetupAllowed": false
        }
      ]
    },
    {
      "id": "0efb64e6-b334-4e0e-92d2-bfe9ce76ce78",
      "alias": "Direct Grant - Conditional OTP",
      "description": "Flow to determine if the OTP is required for the authentication",
      "providerId": "basic-flow",
      "topLevel": false,
      "builtIn": true,
      "authenticationExecutions": [
        {
          "authenticator": "conditional-user-configured",
          "authenticatorFlow": false,
          "requirement": "REQUIRED",
          "priority": 10,
          "autheticatorFlow": false,
          "userSetupAllowed": false
        },
        {
          "authenticator": "direct-grant-validate-otp",
          "authenticatorFlow": false,
          "requirement": "REQUIRED",
          "priority": 20,
          "autheticatorFlow": false,
          "userSetupAllowed": false
        }
      ]
    },
    {
      "id": "88efe807-91f7-45c2-8971-0cd77eed72fb",
      "alias": "First broker login - Conditional OTP",
      "description": "Flow to determine if the OTP is required for the authentication",
      "providerId": "basic-flow",
      "topLevel": false,
      "builtIn": true,
      "authenticationExecutions": [
        {
          "authenticator": "conditional-user-configured",
          "authenticatorFlow": false,
          "requirement": "REQUIRED",
          "priority": 10,
          "autheticatorFlow": false,
          "userSetupAllowed": false
        },
        {
          "authenticator": "auth-otp-form",
          "authenticatorFlow": false,
          "requirement": "REQUIRED",
          "priority": 20,
          "autheticatorFlow": false,
          "userSetupAllowed": false
        }
      ]
    },
    {
      "id": "402d4ae1-068e-4b7e-8740-683c092624f2",
      "alias": "Handle Existing Account",
      "description": "Handle what to do if there is existing account with same email/username like authenticated identity provider",
      "providerId": "basic-flow",
      "topLevel": false,
      "builtIn": true,
      "authenticationExecutions": [
        {
          "authenticator": "idp-confirm-link",
          "authenticatorFlow": false,
          "requirement": "REQUIRED",
          "priority": 10,
          "autheticatorFlow": false,
          "userSetupAllowed": false
        },
        {
          "authenticatorFlow": true,
          "requirement": "REQUIRED",
          "priority": 20,
          "autheticatorFlow": true,
          "flowAlias": "Account verification options",
          "userSetupAllowed": false
        }
      ]
    },
    {
      "id": "32f2f5b8-ca74-4d0b-88c2-271fc54b298a",
      "alias": "Reset - Conditional OTP",
      "description": "Flow to determine if the OTP should be reset or not. Set to REQUIRED to force.",
      "providerId": "basic-flow",
      "topLevel": false,
      "builtIn": true,
      "authenticationExecutions": [
        {
          "authenticator": "conditional-user-configured",
          "authenticatorFlow": false,
          "requirement": "REQUIRED",
          "priority": 10,
          "autheticatorFlow": false,
          "userSetupAllowed": false
        },
        {
          "authenticator": "reset-otp",
          "authenticatorFlow": false,
          "requirement": "REQUIRED",
          "priority": 20,
          "autheticatorFlow": false,
          "userSetupAllowed": false
        }
      ]
    },
    {
      "id": "6708a3bc-7717-445c-b959-456423a69b12",
      "alias": "User creation or linking",
      "description": "Flow for the existing/non-existing user alternatives",
      "providerId": "basic-flow",
      "topLevel": false,
      "builtIn": true,
      "authenticationExecutions": [
        {
          "authenticatorConfig": "create unique user config",
          "authenticator": "idp-create-user-if-unique",
          "authenticatorFlow": false,
          "requirement": "ALTERNATIVE",
          "priority": 10,
          "autheticatorFlow": false,
          "userSetupAllowed": false
        },
        {
          "authenticatorFlow": true,
          "requirement": "ALTERNATIVE",
          "priority": 20,
          "autheticatorFlow": true,
          "flowAlias": "Handle Existing Account",
          "userSetupAllowed": false
        }
      ]
    },
    {
      "id": "b9f516d3-69ab-4fbf-b96d-227d74beb335",
      "alias": "Verify Existing Account by Re-authentication",
      "description": "Reauthentication of existing account",
      "providerId": "basic-flow",
      "topLevel": false,
      "builtIn": true,
      "authenticationExecutions": [
        {
          "authenticator": "idp-username-password-form",
          "authenticatorFlow": false,
          "requirement": "REQUIRED",
          "priority": 10,
          "autheticatorFlow": false,
          "userSetupAllowed": false
        },
        {
          "authenticatorFlow": true,
          "requirement": "CONDITIONAL",
          "priority": 20,
          "autheticatorFlow": true,
          "flowAlias": "First broker login - Conditional OTP",
          "userSetupAllowed": false
        }
      ]
    },
    {
      "id": "3b01d510-dd10-43d8-897c-604f6edf6104",
      "alias": "browser",
      "description": "browser based authentication",
      "providerId": "basic-flow",
      "topLevel": true,
      "builtIn": true,
      "authenticationExecutions": [
        {
          "authenticator": "auth-cookie",
          "authenticatorFlow": false,
          "requirement": "ALTERNATIVE",
          "priority": 10,
          "autheticatorFlow": false,
          "userSetupAllowed": false
        },
        {
          "authenticator": "auth-spnego",
          "authenticatorFlow": false,
          "requirement": "DISABLED",
          "priority": 20,
          "autheticatorFlow": false,
          "userSetupAllowed": false
        },
        {
          "authenticator": "identity-provider-redirector",
          "authenticatorFlow": false,
          "requirement": "ALTERNATIVE",
          "priority": 25,
          "autheticatorFlow": false,
          "userSetupAllowed": false
        },
        {
          "authenticatorFlow": true,
          "requirement": "ALTERNATIVE",
          "priority": 30,
          "autheticatorFlow": true,
          "flowAlias": "forms",
          "userSetupAllowed": false
        }
      ]
    },
    {
      "id": "76f34715-e513-4982-8fdc-7d60122bd0ab",
      "alias": "clients",
      "description": "Base authentication for clients",
      "providerId": "client-flow",
      "topLevel": true,
      "builtIn": true,
      "authenticationExecutions": [
        {
          "authenticator": "client-secret",
          "authenticatorFlow": false,
          "requirement": "ALTERNATIVE",
          "priority": 10,
          "autheticatorFlow": false,
          "userSetupAllowed": false
        },
        {
          "authenticator": "client-jwt",
          "authenticatorFlow": false,
          "requirement": "ALTERNATIVE",
          "priority": 20,
          "autheticatorFlow": false,
          "userSetupAllowed": false
        },
        {
          "authenticator": "client-secret-jwt",
          "authenticatorFlow": false,
          "requirement": "ALTERNATIVE",
          "priority": 30,
          "autheticatorFlow": false,
          "userSetupAllowed": false
        },
        {
          "authenticator": "client-x509",
          "authenticatorFlow": false,
          "requirement": "ALTERNATIVE",
          "priority": 40,
          "autheticatorFlow": false,
          "userSetupAllowed": false
        }
      ]
    },
    {
      "id": "8bc39bc7-f3af-415f-ba5e-c065e4d8db62",
      "alias": "direct grant",
      "description": "OpenID Connect Resource Owner Grant",
      "providerId": "basic-flow",
      "topLevel": true,
      "builtIn": true,
      "authenticationExecutions": [
        {
          "authenticator": "direct-grant-validate-username",
          "authenticatorFlow": false,
          "requirement": "REQUIRED",
          "priority": 10,
          "autheticatorFlow": false,
          "userSetupAllowed": false
        },
        {
          "authenticator": "direct-grant-validate-password",
          "authenticatorFlow": false,
          "requirement": "REQUIRED",
          "priority": 20,
          "autheticatorFlow": false,
          "userSetupAllowed": false
        },
        {
          "authenticatorFlow": true,
          "requirement": "CONDITIONAL",
          "priority": 30,
          "autheticatorFlow": true,
          "flowAlias": "Direct Grant - Conditional OTP",
          "userSetupAllowed": false
        }
      ]
    },
    {
      "id": "ebf343e2-25cc-4ba6-9f58-fae3b31b7481",
      "alias": "docker auth",
      "description": "Used by Docker clients to authenticate against the IDP",
      "providerId": "basic-flow",
      "topLevel": true,
      "builtIn": true,
      "authenticationExecutions": [
        {
          "authenticator": "docker-http-basic-authenticator",
          "authenticatorFlow": false,
          "requirement": "REQUIRED",
          "priority": 10,
          "autheticatorFlow": false,
          "userSetupAllowed": false
        }
      ]
    },
    {
      "id": "389bd2eb-60b0-40a6-bfd9-4e9b5546472e",
      "alias": "first broker login",
      "description": "Actions taken after first broker login with identity provider account, which is not yet linked to any Keycloak account",
      "providerId": "basic-flow",
      "topLevel": true,
      "builtIn": true,
      "authenticationExecutions": [
        {
          "authenticatorConfig": "review profile config",
          "authenticator": "idp-review-profile",
          "authenticatorFlow": false,
          "requirement": "REQUIRED",
          "priority": 10,
          "autheticatorFlow": false,
          "userSetupAllowed": false
        },
        {
          "authenticatorFlow": true,
          "requirement": "REQUIRED",
          "priority": 20,
          "autheticatorFlow": true,
          "flowAlias": "User creation or linking",
          "userSetupAllowed": false
        }
      ]
    },
    {
      "id": "4088a711-d8b9-48d2-89cc-723b045fe3d1",
      "alias": "forms",
      "description": "Username, password, otp and other auth forms.",
      "providerId": "basic-flow",
      "topLevel": false,
      "builtIn": true,
      "authenticationExecutions": [
        {
          "authenticator": "auth-username-password-form",
          "authenticatorFlow": false,
          "requirement": "REQUIRED",
          "priority": 10,
          "autheticatorFlow": false,
          "userSetupAllowed": false
        },
        {
          "authenticatorFlow": true,
          "requirement": "CONDITIONAL",
          "priority": 20,
          "autheticatorFlow": true,
          "flowAlias": "Browser - Conditional OTP",
          "userSetupAllowed": false
        }
      ]
    },
    {
      "id": "4324444b-fbbc-4f4c-891c-c3883e6ae4d8",
      "alias": "http challenge",
      "description": "An authentication flow based on challenge-response HTTP Authentication Schemes",
      "providerId": "basic-flow",
      "topLevel": true,
      "builtIn": true,
      "authenticationExecutions": [
        {
          "authenticator": "no-cookie-redirect",
          "authenticatorFlow": false,
          "requirement": "REQUIRED",
          "priority": 10,
          "autheticatorFlow": false,
          "userSetupAllowed": false
        },
        {
          "authenticatorFlow": true,
          "requirement": "REQUIRED",
          "priority": 20,
          "autheticatorFlow": true,
          "flowAlias": "Authentication Options",
          "userSetupAllowed": false
        }
      ]
    },
    {
      "id": "0f8f8f57-b6d5-48d3-a567-10280c47de3e",
      "alias": "registration",
      "description": "registration flow",
      "providerId": "basic-flow",
      "topLevel": true,
      "builtIn": true,
      "authenticationExecutions": [
        {
          "authenticator": "registration-page-form",
          "authenticatorFlow": true,
          "requirement": "REQUIRED",
          "priority": 10,
          "autheticatorFlow": true,
          "flowAlias": "registration form",
          "userSetupAllowed": false
        }
      ]
    },
    {
      "id": "cd92dd04-469a-408b-a294-128e16371e60",
      "alias": "registration form",
      "description": "registration form",
      "providerId": "form-flow",
      "topLevel": false,
      "builtIn": true,
      "authenticationExecutions": [
        {
          "authenticator": "registration-user-creation",
          "authenticatorFlow": false,
          "requirement": "REQUIRED",
          "priority": 20,
          "autheticatorFlow": false,
          "userSetupAllowed": false
        },
        {
          "authenticator": "registration-profile-action",
          "authenticatorFlow": false,
          "requirement": "REQUIRED",
          "priority": 40,
          "autheticatorFlow": false,
          "userSetupAllowed": false
        },
        {
          "authenticator": "registration-password-action",
          "authenticatorFlow": false,
          "requirement": "REQUIRED",
          "priority": 50,
          "autheticatorFlow": false,
          "userSetupAllowed": false
        },
        {
          "authenticator": "registration-recaptcha-action",
          "authenticatorFlow": false,
          "requirement": "DISABLED",
          "priority": 60,
          "autheticatorFlow": false,
          "userSetupAllowed": false
        }
      ]
    },
    {
      "id": "32a4eb3e-dd3c-41f7-8426-f81b0e169dc5",
      "alias": "reset credentials",
      "description": "Reset credentials for a user if they forgot their password or something",
      "providerId": "basic-flow",
      "topLevel": true,
      "builtIn": true,
      "authenticationExecutions": [
        {
          "authenticator": "reset-credentials-choose-user",
          "authenticatorFlow": false,
          "requirement": "REQUIRED",
          "priority": 10,
          "autheticatorFlow": false,
          "userSetupAllowed": false
        },
        {
          "authenticator": "reset-credential-email",
          "authenticatorFlow": false,
          "requirement": "REQUIRED",
          "priority": 20,
          "autheticatorFlow": false,
          "userSetupAllowed": false
        },
        {
          "authenticator": "reset-password",
          "authenticatorFlow": false,
          "requirement": "REQUIRED",
          "priority": 30,
          "autheticatorFlow": false,
          "userSetupAllowed": false
        },
        {
          "authenticatorFlow": true,
          "requirement": "CONDITIONAL",
          "priority": 40,
          "autheticatorFlow": true,
          "flowAlias": "Reset - Conditional OTP",
          "userSetupAllowed": false
        }
      ]
    },
    {
      "id": "e7aa1ef3-f58d-405c-a325-43b3afac598d",
      "alias": "saml ecp",
      "description": "SAML ECP Profile Authentication Flow",
      "providerId": "basic-flow",
      "topLevel": true,
      "builtIn": true,
      "authenticationExecutions": [
        {
          "authenticator": "http-basic-authenticator",
          "authenticatorFlow": false,
          "requirement": "REQUIRED",
          "priority": 10,
          "autheticatorFlow": false,
          "userSetupAllowed": false
        }
      ]
    }
  ],
  "authenticatorConfig": [
    {
      "id": "cdbc61be-b3cb-4a31-b76e-6fead8009218",
      "alias": "create unique user config",
      "config": {
        "require.password.update.after.registration": "false"
      }
    },
    {
      "id": "86d9714a-5f71-43a2-9ac6-2027bb364403",
      "alias": "review profile config",
      "config": {
        "update.profile.on.first.login": "missing"
      }
    }
  ],
  "requiredActions": [
    {
      "alias": "CONFIGURE_TOTP",
      "name": "Configure OTP",
      "providerId": "CONFIGURE_TOTP",
      "enabled": true,
      "defaultAction": false,
      "priority": 10,
      "config": {}
    },
    {
      "alias": "terms_and_conditions",
      "name": "Terms and Conditions",
      "providerId": "terms_and_conditions",
      "enabled": false,
      "defaultAction": false,
      "priority": 20,
      "config": {}
    },
    {
      "alias": "UPDATE_PASSWORD",
      "name": "Update Password",
      "providerId": "UPDATE_PASSWORD",
      "enabled": true,
      "defaultAction": false,
      "priority": 30,
      "config": {}
    },
    {
      "alias": "UPDATE_PROFILE",
      "name": "Update Profile",
      "providerId": "UPDATE_PROFILE",
      "enabled": true,
      "defaultAction": false,
      "priority": 40,
      "config": {}
    },
    {
      "alias": "VERIFY_EMAIL",
      "name": "Verify Email",
      "providerId": "VERIFY_EMAIL",
      "enabled": true,
      "defaultAction": false,
      "priority": 50,
      "config": {}
    },
    {
      "alias": "delete_account",
      "name": "Delete Account",
      "providerId": "delete_account",
      "enabled": false,
      "defaultAction": false,
      "priority": 60,
      "config": {}
    },
    {
      "alias": "update_user_locale",
      "name": "Update User Locale",
      "providerId": "update_user_locale",
      "enabled": true,
      "defaultAction": false,
      "priority": 1000,
      "config": {}
    }
  ],
  "browserFlow": "browser",
  "registrationFlow": "registration",
  "directGrantFlow": "direct grant",
  "resetCredentialsFlow": "reset credentials",
  "clientAuthenticationFlow": "clients",
  "dockerAuthenticationFlow": "docker auth",
  "attributes": {
    "cibaBackchannelTokenDeliveryMode": "poll",
    "cibaAuthRequestedUserHint": "login_hint",
    "oauth2DevicePollingInterval": "5",
    "clientOfflineSessionMaxLifespan": "0",
    "clientSessionIdleTimeout": "0",
    "userProfileEnabled": "false",
    "clientOfflineSessionIdleTimeout": "0",
    "cibaInterval": "5",
    "cibaExpiresIn": "120",
    "oauth2DeviceCodeLifespan": "600",
    "parRequestUriLifespan": "60",
    "clientSessionMaxLifespan": "0",
    "frontendUrl": "${REALM_FRONTEND_URL}"
  },
  "keycloakVersion": "18.0.1",
  "userManagedAccessAllowed": true,
  "clientProfiles": {
    "profiles": []
  },
  "clientPolicies": {
    "policies": []
  }
}